tiktokapipy/__init__.py
tiktokapipy/api.py
tiktokapipy/async_api.py
tiktokapipy/models/__init__.py
tiktokapipy/models/challenge.py
tiktokapipy/models/comment.py
tiktokapipy/models/raw_data.py
tiktokapipy/models/user.py
tiktokapipy/models/video.py
tiktokapipy/util/__init__.py
tiktokapipy/util/deferred_collectors.py
tiktokapipy/util/queries.py
tiktokapipy/util/signing.py
tiktokapipy-0.2.4.post2.dist-info/LICENSE
tiktokapipy-0.2.4.post2.dist-info/METADATA
tiktokapipy-0.2.4.post2.dist-info/WHEEL
tiktokapipy-0.2.4.post2.dist-info/top_level.txt
tiktokapipy-0.2.4.post2.dist-info/RECORD
