Metadata-Version: 2.1
Name: tiktokapipy
Version: 0.2.4.post2
Summary: Asyncio TikTok data scraping tool
Author-email: Russell Newton <russell.newton01@gmail.com>
Project-URL: Homepage, https://github.com/Russell-Newton/TikTokPy
Project-URL: Documentation, https://tiktokpy.readthedocs.io/en/latest/
Keywords: tiktok,python3,scraper,unofficial,tiktok-scraper,tiktok scraper,asyncio,playwright-python
Classifier: Development Status :: 3 - Alpha
Classifier: Framework :: AsyncIO
Classifier: Intended Audience :: Developers
Classifier: Intended Audience :: Information Technology
Classifier: Intended Audience :: Science/Research
Classifier: License :: OSI Approved :: MIT License
Classifier: Operating System :: OS Independent
Classifier: Programming Language :: Python :: 3
Classifier: Programming Language :: Python :: 3.8
Classifier: Programming Language :: Python :: 3.9
Classifier: Programming Language :: Python :: 3.10
Classifier: Programming Language :: Python :: 3.11
Classifier: Topic :: Games/Entertainment
Classifier: Topic :: Software Development :: Libraries :: Python Modules
Requires-Python: >=3.8
License-File: LICENSE
Requires-Dist: playwright~=1.29
Requires-Dist: pydantic>=2
Requires-Dist: requests
Provides-Extra: test
Requires-Dist: pytest; extra == "test"
Requires-Dist: pytest-cov; extra == "test"
Requires-Dist: pytest-asyncio; extra == "test"
Requires-Dist: tox; extra == "test"
Provides-Extra: docs
Requires-Dist: toml; extra == "docs"
Requires-Dist: docutils>=0.18; extra == "docs"
Requires-Dist: sphinx<7; extra == "docs"
Requires-Dist: sphinx-rtd-theme; extra == "docs"
Requires-Dist: sphinx-autodoc-typehints; extra == "docs"
Requires-Dist: sphinx-tabs; extra == "docs"
Requires-Dist: mock; extra == "docs"
Provides-Extra: download
Requires-Dist: yt-dlp; extra == "download"
